AsyncURLCrawler/__init__.py
AsyncURLCrawler/crawler.py
AsyncURLCrawler/parser.py
AsyncURLCrawler/url_utils.py
asyncurlcrawler-0.0.4.dist-info/METADATA
asyncurlcrawler-0.0.4.dist-info/WHEEL
asyncurlcrawler-0.0.4.dist-info/licenses/LICENSE
asyncurlcrawler-0.0.4.dist-info/RECORD
