Metadata-Version: 2.3
Name: AsyncURLCrawler
Version: 0.0.4
Summary: AsyncURLCrawler navigates through web pages concurrently by following hyperlinks to collect URLs.
Project-URL: Homepage, https://github.com/PouyaEsmaeili/AsyncURLCrawler
Project-URL: Issues, https://github.com/PouyaEsmaeili/AsyncURLCrawler/issues
Author-email: Pouya Esameili <pouya.esmaeili.g@gmail.com>
License-File: LICENSE
Classifier: License :: OSI Approved :: MIT License
Classifier: Operating System :: OS Independent
Classifier: Programming Language :: Python :: 3
Requires-Python: >=3.8
